google-stubs/METADATA.toml
google-stubs/cloud/ndb/__init__.pyi
google-stubs/cloud/ndb/_batch.pyi
google-stubs/cloud/ndb/_cache.pyi
google-stubs/cloud/ndb/_datastore_api.pyi
google-stubs/cloud/ndb/_datastore_query.pyi
google-stubs/cloud/ndb/_eventloop.pyi
google-stubs/cloud/ndb/_options.pyi
google-stubs/cloud/ndb/_transaction.pyi
google-stubs/cloud/ndb/blobstore.pyi
google-stubs/cloud/ndb/client.pyi
google-stubs/cloud/ndb/context.pyi
google-stubs/cloud/ndb/django_middleware.pyi
google-stubs/cloud/ndb/exceptions.pyi
google-stubs/cloud/ndb/global_cache.pyi
google-stubs/cloud/ndb/key.pyi
google-stubs/cloud/ndb/metadata.pyi
google-stubs/cloud/ndb/model.pyi
google-stubs/cloud/ndb/msgprop.pyi
google-stubs/cloud/ndb/polymodel.pyi
google-stubs/cloud/ndb/py.typed
google-stubs/cloud/ndb/query.pyi
google-stubs/cloud/ndb/stats.pyi
google-stubs/cloud/ndb/tasklets.pyi
google-stubs/cloud/ndb/utils.pyi
google-stubs/cloud/ndb/version.pyi
types_google_cloud_ndb-2.3.0.20250317.dist-info/LICENSE
types_google_cloud_ndb-2.3.0.20250317.dist-info/METADATA
types_google_cloud_ndb-2.3.0.20250317.dist-info/WHEEL
types_google_cloud_ndb-2.3.0.20250317.dist-info/top_level.txt
types_google_cloud_ndb-2.3.0.20250317.dist-info/RECORD
